{
  "_comment": "Auto-generated by scripts/update-verification-counts.sh — DO NOT EDIT MANUALLY",
  "_updated": "2026-02-05T06:30:00Z",
  "_source": "Parsed from actual source files (not hardcoded)",
  "grand_total": 2856,
  "verus": {
    "total": 475,
    "vec2": 55,
    "vec3": 55,
    "vec4": 55,
    "mat3": 48,
    "mat3_base": 22,
    "mat3_extended": 26,
    "mat4": 54,
    "mat4_base": 22,
    "mat4_extended": 32,
    "color": 57,
    "rect": 52,
    "bounds": 66,
    "utils": 33
  },
  "coq_r": {
    "total": 1366,
    "vec2": 139,
    "vec3": 133,
    "vec4": 96,
    "mat3": 102,
    "mat4": 208,
    "color": 164,
    "rect": 218,
    "complexity": 60,
    "utils": 59,
    "crosstype": 51,
    "bounds": 136
  },
  "coq_z": {
    "total": 429,
    "vec2": 62,
    "vec3": 54,
    "vec4": 39,
    "mat3": 25,
    "mat4": 50,
    "color": 60,
    "rect": 51,
    "utils": 18,
    "bounds": 70
  },
  "coq_fp": {
    "total": 361,
    "common": 6,
    "rounding": 34,
    "error_bounds": 48,
    "vec": 48,
    "mat": 50,
    "color": 48,
    "rect": 45,
    "bounds": 45,
    "utils": 37
  },
  "coq_combined": 1795,
  "coq_all": 2156,
  "kani": {
    "total": 225,
    "vec2": 28,
    "vec3": 29,
    "vec4": 25,
    "mat3": 23,
    "mat4": 32,
    "color": 25,
    "rect": 27,
    "bounds": 25,
    "utils": 11
  },
  "per_type": {
    "vec2": 284,
    "vec3": 271,
    "vec4": 215,
    "mat3": 198,
    "mat4": 344,
    "color": 306,
    "rect": 348,
    "utils": 121,
    "bounds": 297,
    "complexity": 60
  },
  "optimization_phases": 83
}
